odoo/addons/shopinvader_schema_invoice/README.rst
odoo/addons/shopinvader_schema_invoice/__init__.py
odoo/addons/shopinvader_schema_invoice/__manifest__.py
odoo/addons/shopinvader_schema_invoice/i18n/shopinvader_schema_invoice.pot
odoo/addons/shopinvader_schema_invoice/readme/CONTRIBUTORS.rst
odoo/addons/shopinvader_schema_invoice/readme/DESCRIPTION.rst
odoo/addons/shopinvader_schema_invoice/schemas/__init__.py
odoo/addons/shopinvader_schema_invoice/schemas/amount.py
odoo/addons/shopinvader_schema_invoice/schemas/invoice.py
odoo/addons/shopinvader_schema_invoice/static/description/index.html
odoo/addons/shopinvader_schema_invoice/tests/__init__.py
odoo/addons/shopinvader_schema_invoice/tests/common.py
odoo/addons/shopinvader_schema_invoice/tests/test_invoice_schema.py
odoo_addon_shopinvader_schema_invoice-16.0.1.0.1.dist-info/METADATA
odoo_addon_shopinvader_schema_invoice-16.0.1.0.1.dist-info/WHEEL
odoo_addon_shopinvader_schema_invoice-16.0.1.0.1.dist-info/top_level.txt
odoo_addon_shopinvader_schema_invoice-16.0.1.0.1.dist-info/RECORD
